dubletten_tool/__init__.py
dubletten_tool/admin.py
dubletten_tool/apps.py
dubletten_tool/auto_script.py
dubletten_tool/create_datasets.py
dubletten_tool/detail_view.py
dubletten_tool/dump_improvements/ReMergeCleanScript_Verbesserung.ipynb
dubletten_tool/dump_improvements/helper_functions/helper_functions.py
dubletten_tool/dump_improvements/helper_functions/loggers.py
dubletten_tool/forms.py
dubletten_tool/grouping_script_1.py
dubletten_tool/helpers.py
dubletten_tool/logger.py
dubletten_tool/management/__init__.py
dubletten_tool/management/commands/__init__.py
dubletten_tool/management/commands/add_access_groups.py
dubletten_tool/management/commands/merge_groups.py
dubletten_tool/management/commands/setup_groups.py
dubletten_tool/merge_filters.py
dubletten_tool/merge_functions.py
dubletten_tool/merge_tables.py
dubletten_tool/merge_views.py
dubletten_tool/migrations/0001_initial.py
dubletten_tool/migrations/0002_dublettenlog.py
dubletten_tool/migrations/0003_ampel.py
dubletten_tool/migrations/0004_auto_20221026_1855.py
dubletten_tool/migrations/0005_alter_ampel_status.py
dubletten_tool/migrations/0006_delete_ampel.py
dubletten_tool/migrations/0007_group_vorfin.py
dubletten_tool/migrations/0008_alter_group_vorfin.py
dubletten_tool/migrations/__init__.py
dubletten_tool/models.py
dubletten_tool/src/classes/ErrorLoggerMixin.py
dubletten_tool/src/classes/MergeGroup.py
dubletten_tool/src/classes/PPHelper.py
dubletten_tool/src/classes/PPKind.py
dubletten_tool/src/classes/PersonHelper.py
dubletten_tool/src/classes/PersonType.py
dubletten_tool/src/classes/ProcessingTracker.py
dubletten_tool/src/classes/RelationWriter.py
dubletten_tool/src/classes/RemergeHelper.py
dubletten_tool/src/classes/TempRel.py
dubletten_tool/src/classes/__init__.py
dubletten_tool/src/classes/class_notes.md
dubletten_tool/src/functions/helper_functions.py
dubletten_tool/src/functions/remerge_single_group.py
dubletten_tool/static/dubletten_tool/css/main_dubletten.css
dubletten_tool/suggestions.py
dubletten_tool-0.2.1.dist-info/WHEEL
dubletten_tool-0.2.1.dist-info/METADATA
dubletten_tool-0.2.1.dist-info/RECORD
