Metadata-Version: 2.1
Name: dubletten-tool
Version: 0.2.1
Summary: APIS module for the VieCPro instance to perform manual deduplication of person instances
Author: Gregor Pirgie
Author-email: gregor.pirgie@oeaw.ac.at
Requires-Python: >=3.8
Classifier: Programming Language :: Python :: 3
Classifier: Programming Language :: Python :: 3.8
Classifier: Programming Language :: Python :: 3.9
Classifier: Programming Language :: Python :: 3.10
Classifier: Programming Language :: Python :: 3.11
Requires-Dist: python-Levenshtein (>=0.12.2,<0.13.0)
